ansys/simai/core/__init__.py
ansys/simai/core/client.py
ansys/simai/core/errors.py
ansys/simai/core/py.typed
ansys/simai/core/api/__init__.py
ansys/simai/core/api/client.py
ansys/simai/core/api/geometry.py
ansys/simai/core/api/mixin.py
ansys/simai/core/api/optimization.py
ansys/simai/core/api/point_cloud.py
ansys/simai/core/api/post_processing.py
ansys/simai/core/api/prediction.py
ansys/simai/core/api/project.py
ansys/simai/core/api/sse.py
ansys/simai/core/api/training_data.py
ansys/simai/core/api/training_data_part.py
ansys/simai/core/api/workspace.py
ansys/simai/core/api/geomai/__init__.py
ansys/simai/core/api/geomai/predictions.py
ansys/simai/core/api/geomai/projects.py
ansys/simai/core/api/geomai/training_data.py
ansys/simai/core/api/geomai/training_data_parts.py
ansys/simai/core/api/geomai/workspaces.py
ansys/simai/core/data/__init__.py
ansys/simai/core/data/base.py
ansys/simai/core/data/downloads.py
ansys/simai/core/data/geometries.py
ansys/simai/core/data/geometry_utils.py
ansys/simai/core/data/global_coefficients_requests.py
ansys/simai/core/data/lists.py
ansys/simai/core/data/model_configuration.py
ansys/simai/core/data/models.py
ansys/simai/core/data/optimizations.py
ansys/simai/core/data/post_processings.py
ansys/simai/core/data/predictions.py
ansys/simai/core/data/projects.py
ansys/simai/core/data/selection_post_processings.py
ansys/simai/core/data/selections.py
ansys/simai/core/data/training_data.py
ansys/simai/core/data/training_data_parts.py
ansys/simai/core/data/types.py
ansys/simai/core/data/workspaces.py
ansys/simai/core/data/geomai/__init__.py
ansys/simai/core/data/geomai/client.py
ansys/simai/core/data/geomai/models.py
ansys/simai/core/data/geomai/predictions.py
ansys/simai/core/data/geomai/projects.py
ansys/simai/core/data/geomai/training_data.py
ansys/simai/core/data/geomai/training_data_parts.py
ansys/simai/core/data/geomai/workspaces.py
ansys/simai/core/utils/__init__.py
ansys/simai/core/utils/auth.py
ansys/simai/core/utils/config_file.py
ansys_simai_core-0.3.7.dist-info/METADATA
ansys_simai_core-0.3.7.dist-info/WHEEL
ansys_simai_core-0.3.7.dist-info/licenses/AUTHORS
ansys_simai_core-0.3.7.dist-info/licenses/LICENSE
ansys_simai_core-0.3.7.dist-info/RECORD
