Metadata-Version: 2.4
Name: ansys-simai-core
Version: 0.3.7
Summary: A python wrapper for Ansys SimAI
Project-URL: Bugs, https://github.com/ansys/pysimai/issues
Project-URL: Documentation, https://simai.docs.pyansys.com
Project-URL: Source, https://github.com/ansys/pysimai
Project-URL: Discussions, https://github.com/ansys/pysimai/discussions
Project-URL: Releases, https://github.com/ansys/pysimai/releases
Author-email: "ANSYS, Inc." <pyansys.core@ansys.com>
Maintainer-email: PyAnsys developers <pyansys.maintainers@ansys.com>
License: MIT License
License-File: AUTHORS
License-File: LICENSE
Classifier: Development Status :: 3 - Alpha
Classifier: Intended Audience :: Science/Research
Classifier: License :: OSI Approved :: MIT License
Classifier: Operating System :: OS Independent
Classifier: Programming Language :: Python :: 3.9
Classifier: Programming Language :: Python :: 3.10
Classifier: Programming Language :: Python :: 3.11
Classifier: Programming Language :: Python :: 3.12
Classifier: Programming Language :: Python :: 3.13
Classifier: Topic :: Scientific/Engineering :: Artificial Intelligence
Classifier: Topic :: Scientific/Engineering :: Information Analysis
Classifier: Topic :: Scientific/Engineering :: Physics
Requires-Python: <4,>=3.9
Requires-Dist: filelock>=3.10.7
Requires-Dist: httpx-retries>=0.4.2
Requires-Dist: httpx-sse>=0.4.1
Requires-Dist: httpx>=0.28.1
Requires-Dist: pydantic<3,>=2.5.1
Requires-Dist: semver>=3.0.2
Requires-Dist: tomli<3,>=2.0.1
Requires-Dist: tqdm>=4.66.1
Requires-Dist: truststore>=0.10.0; python_version >= '3.10'
Requires-Dist: typing-extensions>=4.12.0
Requires-Dist: wakepy>=0.8.0
